{
  "roots": {
    "taku": "see/look",
    "inuk": "person",
    "aalisakkat": "fish",
    "aalisa": "fish",
    "nuna": "land",
    "kalaallit": "Greenlander",
    "suli": "work",
    "angi": "big",
    "ikinngut": "friend",
    "ataata": "father",
    "anaana": "mother",
    "illu": "house",
    "qimmeq": "dog",
    "nerivoq": "eat",
    "pisuppoq": "walk",
    "kingorna": "after/behind",
    "kinguneq": "back/rear",
    "nalunaarusiortarpoq": "report/write_report",
    "misissuineq": "inspection"
  },
  "tags": {
    "V": "Verb",
    "N": "Noun",
    "A": "Adjective",
    "Adv": "Adverb",
    "Ind": "Indicative",
    "Imp": "Imperative",
    "Int": "Interrogative",
    "1Sg": "1sg (I)",
    "2Sg": "2sg (you)",
    "3Sg": "3sg (he/she/it)",
    "1Pl": "1pl (we)",
    "2Pl": "2pl (you.all)",
    "3Pl": "3pl (they)",
    "1SgO": "→me",
    "2SgO": "→you",
    "3SgO": "→him/her/it",
    "1PlO": "→us",
    "2PlO": "→you.all",
    "3PlO": "→them",
    "Sg": "singular",
    "Pl": "plural",
    "Abs": "absolutive",
    "Rel": "relative",
    "Trm": "terminalis",
    "Lok": "locative",
    "Abl": "ablative",
    "Via": "via/through",
    "Gram/TV": "transitive",
    "Gram/IV": "intransitive",
    "Gram/HV": "half-transitive",
    "Gram/Refl": "reflexive",
    "Der/vv": "V→V",
    "SSA": "FUT/intention",
    "NNGIT": "NEG",
    "GALUAR": "but",
    "LI": "also",
    "Pali": "again",
    "3SgPoss": "his/her/its",
    "3PlPoss": "their",
    "1SgPoss": "my",
    "2SgPoss": "your",
    "CLB": "."
  }
}
